kill_timeout.py
kill_timeout-0.0.3.dist-info/AUTHORS
kill_timeout-0.0.3.dist-info/METADATA
kill_timeout-0.0.3.dist-info/WHEEL
kill_timeout-0.0.3.dist-info/pbr.json
kill_timeout-0.0.3.dist-info/top_level.txt
kill_timeout-0.0.3.dist-info/RECORD
