Metadata-Version: 2.1
Name: kill-timeout
Version: 0.0.3
Summary: Limit the function execution time
Home-page: https://github.com/ei-grad/kill-timeout
Author: Andrew Grigorev
Author-email: andrew@ei-grad.ru
License: MIT
Project-URL: Bug Tracker, https://github.com/ei-grad/kill-timeout/issues
Project-URL: Source Code, https://github.com/ei-grad/kill-timeout.git
Keywords: kill,timeout
Platform: UNKNOWN
Classifier: Development Status :: 4 - Beta
Classifier: Intended Audience :: Developers
Classifier: License :: OSI Approved :: MIT License
Classifier: Operating System :: OS Independent
Classifier: Programming Language :: Python
Requires-Python: >=3.7
Requires-Dist: tblib
